vagd/__init__.py
vagd/__main__.py
vagd/box.py
vagd/cli.py
vagd/gdb.py
vagd/helper.py
vagd/templates.py
vagd/wrapper.py
vagd/gdb/__init__.pyi
vagd/gdb/events.pyi
vagd/gdb/printing.pyi
vagd/gdb/prompt.pyi
vagd/gdb/types.pyi
vagd/gdb/unwinder.pyi
vagd/gdb/xmethod.pyi
vagd/res/aliases.txt
vagd/res/seccomp.json
vagd/res/template.txt
vagd/virts/__init__.py
vagd/virts/cogd.py
vagd/virts/dogd.py
vagd/virts/logd.py
vagd/virts/pogd.py
vagd/virts/pwngd.py
vagd/virts/qegd.py
vagd/virts/shgd.py
vagd/virts/vagd.py
vagd-1.7.1.dist-info/licenses/LICENSE
vagd-1.7.1.dist-info/METADATA
vagd-1.7.1.dist-info/WHEEL
vagd-1.7.1.dist-info/entry_points.txt
vagd-1.7.1.dist-info/top_level.txt
vagd-1.7.1.dist-info/RECORD
