Metadata-Version: 2.4
Name: vagd
Version: 1.7.1
Summary: VirtuAlization GDb integrations in pwntools
Author: 0x6fe1be2
Project-URL: Homepage, https://github.com/gfelber/vagd
Project-URL: Documentation, https://gfelber.github.io/vagd/
Project-URL: Bug Tracker, https://github.com/gfelber/vagd/issues
Keywords: vagd,pwn,pwntools,exploit,ctf,capture,the,flag,binary,vagrant,qemu,docker
Classifier: License :: OSI Approved :: GNU General Public License v3 (GPLv3)
Classifier: Programming Language :: Python :: 3
Classifier: Operating System :: POSIX :: Linux
Requires-Python: <3.14,>=3.7
License-File: LICENSE
Requires-Dist: pwntools>=4.14.0
Requires-Dist: docker
Requires-Dist: typer
Requires-Dist: rich
Requires-Dist: podman
Dynamic: license-file
